{
    "name": "MySwap Tokens",
    "logoURI": "https://swap.tronfund.xyz/images/aaa.png",
    "keywords": [],
    "tags": {},
    "timestamp": "2020-08-27T00:00:00+00:00",
    "tokens": [
        {
            "chainId": 97,
            "address": "0xE41353b14f5f79A15aCbFb59e4AECA619d25D7C4",
            "symbol": "AAA",
            "name": "AAA Token",
            "decimals": 18,
            "logoURI": "https://swap.tronfund.xyz/images/aaa.png",
            "tags": [
                "datadex",
                "dataproc"
            ]
        },
        {
            "chainId": 97,
            "address": "0xfca31B1B19B0Ef144583A53217Cac84daFD8A204",
            "symbol": "BBB",
            "name": "BBB Token",
            "decimals": 18,
            "logoURI": "https://swap.tronfund.xyz/images/bbb.png",
            "tags": [
                "oracle"
            ]
        }
    ],
    "version": {
        "major": 1,
        "minor": 0,
        "patch": 0
    }
}